{"kind":"identitytoolkit#DownloadAccountResponse","users":[{"localId":"W4nV6EbGCilzVc1cCKbVwzUpahty","createdAt":"1746811139542","lastLoginAt":"1749746405222","passwordHash":"fakeHash:salt=fakeSaltQ4j5KXPDYt1F68lhrC5S:password=9iklp0o*","salt":"fakeSaltQ4j5KXPDYt1F68lhrC5S","passwordUpdatedAt":1750712062289,"providerUserInfo":[{"providerId":"password","email":"uema2yo@gmail.com","federatedId":"uema2yo@gmail.com","rawId":"uema2yo@gmail.com"}],"validSince":"1750712062","email":"uema2yo@gmail.com","emailVerified":false,"disabled":false},{"localId":"gO1FAyg26tbOcNdpmd31p8VSyBsa","createdAt":"1746986769521","lastLoginAt":"1750712138769","passwordHash":"fakeHash:salt=fakeSaltgpNaH4WFez6jbh1MA5qA:password=9iklp0o*","salt":"fakeSaltgpNaH4WFez6jbh1MA5qA","passwordUpdatedAt":1750712062289,"providerUserInfo":[{"providerId":"password","email":"uema2yo+2@gmail.com","federatedId":"uema2yo+2@gmail.com","rawId":"uema2yo+2@gmail.com"}],"validSince":"1750712062","email":"uema2yo+2@gmail.com","emailVerified":false,"disabled":false,"lastRefreshAt":"2025-06-23T20:55:38.769Z"}]}